Metadata-Version: 1.1
Name: bojack
Version: 0.1.1
Summary: BoJack client written in Python
Home-page: https://github.com/mauricioabreu/bojack-py
Author: Mauricio de Abreu Antunes
Author-email: mauricio.abreua@gmail.com
License: MIT
Platform: UNKNOWN
Classifier: Development Status :: 4 - Beta
Classifier: Intended Audience :: Developers
Classifier: Programming Language :: Python :: 3.4
Classifier: Programming Language :: Python :: 3.5
Classifier: Topic :: Software Development :: Libraries :: Python Modules
Classifier: Topic :: System :: Networking
